README.rst
setup.py
pytest_envfiles/__init__.py
pytest_envfiles/plugin.py
pytest_envfiles.egg-info/PKG-INFO
pytest_envfiles.egg-info/SOURCES.txt
pytest_envfiles.egg-info/dependency_links.txt
pytest_envfiles.egg-info/entry_points.txt
pytest_envfiles.egg-info/requires.txt
pytest_envfiles.egg-info/top_level.txt