Metadata-Version: 1.1
Name: pytest-envfiles
Version: 0.1.0
Summary: A py.test plugin that parses environment files before running tests
Home-page: https://github.com/JonnyFunFun/pytest-envfiles
Author: Jonathan Enzinna
Author-email: jonnyfunfun@gmail.com
License: UNKNOWN
Platform: UNKNOWN
Classifier: Development Status :: 3 - Alpha
Classifier: Intended Audience :: Developers
Classifier: License :: OSI Approved :: MIT License
Classifier: Natural Language :: English
Classifier: Programming Language :: Python :: 2
Classifier: Programming Language :: Python :: 2.6
Classifier: Programming Language :: Python :: 2.7
Classifier: Programming Language :: Python :: 3
Classifier: Programming Language :: Python :: 3.3
Classifier: Programming Language :: Python :: 3.4
